FanTree/__init__.py
FanTree/example.py
FanTree-0.2.0.dist-info/LICENSE
FanTree-0.2.0.dist-info/METADATA
FanTree-0.2.0.dist-info/WHEEL
FanTree-0.2.0.dist-info/top_level.txt
FanTree-0.2.0.dist-info/RECORD
